genie_flow_invoker/__init__.py
genie_flow_invoker/class_utils.py
genie_flow_invoker/codec.py
genie_flow_invoker/doc_proc.py
genie_flow_invoker/error_config.py
genie_flow_invoker/factory.py
genie_flow_invoker/genie.py
genie_flow_invoker/pool.py
genie_flow_invoker/utils.py
genie_flow_invoker/invoker/verbatim.py
genie_flow_invoker-0.8.0.dist-info/licenses/NOTICES
genie_flow_invoker-0.8.0.dist-info/METADATA
genie_flow_invoker-0.8.0.dist-info/WHEEL
genie_flow_invoker-0.8.0.dist-info/top_level.txt
genie_flow_invoker-0.8.0.dist-info/RECORD
